[
    {
        "Family_Name": "Johnson",
        "Move_In_Date": "May 13, 2014",
        "Count": 6,
        "Visited_by_Bishopric": false,
        "Individual_Members": [
            {
                "Name": "Peter Kelly",
                "Gender": "Male",
                "Birthdate": "January 18, 1975"
            },
            {
                "Name": "Molly Siepert",
                "Gender": "Female",
                "Birthdate": "March 25, 1978"
            },
            {
                "Name": "Sanders Micheal",
                "Gender": "Male",
                "Birthdate": "December 14, 1995"
            },
            {
                "Name": "Julie Monroe",
                "Gender": "Female",
                "Birthdate": "April 7, 1999"
            },
            {
                "Name": "Milo",
                "Gender": "Male",
                "Birthdate": "August 5, 2004"
            },
            {
                "Name": "Benjiman",
                "Gender":"Male",
                "Birthdate": "March 17, 2006"
            } ] 
    },
    {
        "Family Name": "Smith",
        "Move In Date": "April 20, 2022",
        "Count": 2,
        "Visited by Bishopric": true,
        "Individual Members": [
            {
                "Name": "Joshua Nathaniel",
                "Gender": "Male",
                "Birthdate": "January 5, 1997"
            },
            {
                "Name": "Madison Annie-May",
                "Gender": "Female",
                "Birthdate": "March 17, 2000"
            }
        ]
    }

]